{
    "name": "Tether USD (USDT)",
    "type": "ERC20",
    "symbol": "USDT",
    "decimals": 6,
    "website": "https://tether.to/",
    "description": "desc",
    "explorer": "https://etherscan.io/token/0xdAC17F958D2ee523a2206206994597C13D831ec7",
    "status": "active",
    "id": "0xdAC17F958D2ee523a2206206994597C13D831ec7",
    "links": [
        {
            "name": "github",
            "url": "v1",
            "prefix": "https://github.com/"
        },
        {
            "name": "github",
            "url": null,
            "prefix": "https://github.com/"
        },
        {
            "name": "whitepaper",
            "url": "v2",
            "prefix": ""
        },
        {
            "name": "whitepaper",
            "url": null,
            "prefix": ""
        },
        {
            "name": "blog",
            "url": null,
            "prefix": ""
        }
    ]
}